README.rst
setup.py
pyla/__init__.py
pyla/enteries.py
pyla/exceptions.py
pyla/fields.py
pyla.egg-info/PKG-INFO
pyla.egg-info/SOURCES.txt
pyla.egg-info/dependency_links.txt
pyla.egg-info/requires.txt
pyla.egg-info/top_level.txt