Metadata-Version: 1.0
Name: pyla
Version: 0.1.0b0
Summary: pyla is a redis based storage system
Home-page: http://github.com/dushyant88/pyla
Author: Dushyant Rijhwani
Author-email: dushyant@dush.me
License: UNKNOWN
Platform: UNKNOWN
